.gitignore
LICENSE
MANIFEST.in
Makefile
README.md
requirements.txt
setup.cfg
setup.py
alphabhta/__init__.py
alphabhta/main.py
alphabhta/version.py
alphabhta.egg-info/PKG-INFO
alphabhta.egg-info/SOURCES.txt
alphabhta.egg-info/dependency_links.txt
alphabhta.egg-info/entry_points.txt
alphabhta.egg-info/requires.txt
alphabhta.egg-info/top_level.txt